ts_legalcheck/__init__.py
ts_legalcheck/cli.py
ts_legalcheck/testing.py
ts_legalcheck/utils.py
ts_legalcheck/engine/__init__.py
ts_legalcheck/engine/context.py
ts_legalcheck/engine/marco.py
ts_legalcheck/engine/constraints/__init__.py
ts_legalcheck/engine/constraints/parser/__init__.py
ts_legalcheck/engine/constraints/parser/__main__.py
ts_legalcheck/engine/constraints/parser/grammar.lark
ts_legalcheck/osadl/__init__.py
ts_legalcheck/osadl/__main__.py
ts_legalcheck/osadl/download.py
ts_legalcheck/osadl/transformer/ConstraintsExtractor.py
ts_legalcheck/osadl/transformer/RulesTransformer.py
ts_legalcheck/osadl/transformer/__init__.py
ts_legalcheck/ui/__init__.py
ts_legalcheck/ui/app.py
ts_legalcheck/ui/static/choices.min.css
ts_legalcheck/ui/static/choices.min.js
ts_legalcheck/ui/static/script.js
ts_legalcheck/ui/static/style.css
ts_legalcheck/ui/templates/index.html
ts_legalcheck-1.1.2.dist-info/licenses/LICENSE
ts_legalcheck-1.1.2.dist-info/METADATA
ts_legalcheck-1.1.2.dist-info/WHEEL
ts_legalcheck-1.1.2.dist-info/entry_points.txt
ts_legalcheck-1.1.2.dist-info/top_level.txt
ts_legalcheck-1.1.2.dist-info/RECORD
