Metadata-Version: 2.4
Name: ts-legalcheck
Version: 1.1.2
Summary: TrustSource Legal Check tool.
Author-email: Grigory Markin <gmn@eacg.de>
License-Expression: AGPL-3.0-only
Project-URL: Homepage, https://github.com/trustsource/ts-legalcheck.git
Requires-Python: >=3.10
License-File: LICENSE
Requires-Dist: click~=8.1.7
Requires-Dist: toml~=0.10.2
Requires-Dist: pyyaml~=6.0.2
Requires-Dist: z3-solver==4.15.1.0
Requires-Dist: lark~=1.2.2
Requires-Dist: flask~=3.1.2
Dynamic: license-file
